<?xml version="1.0" encoding="utf-8" ?>
<dwsync>
<file name="choobchindecor-color.png" server="host.somad.ca/kahinpoura/" local="131997468980000000" remote="132002030400000000" Dst="2" />
<file name="choobchindecor_white.png" server="host.somad.ca/kahinpoura/" local="131997464860000000" remote="132002030400000000" Dst="2" />
<file name="CysticFibrosis-color.png" server="host.somad.ca/kahinpoura/" local="131997275100000000" remote="132002030400000000" Dst="2" />
<file name="CysticFibrosis-white.png" server="host.somad.ca/kahinpoura/" local="131997275960000000" remote="132002030400000000" Dst="2" />
<file name="Goal$-color.svg" server="host.somad.ca/kahinpoura/" local="131997272940000000" remote="132002030400000000" Dst="2" />
<file name="Goal$_white.svg" server="host.somad.ca/kahinpoura/" local="131997445880000000" remote="132002030400000000" Dst="2" />
<file name="logo-shipping-color.png" server="host.somad.ca/kahinpoura/" local="132000327680000000" remote="132002030400000000" Dst="2" />
<file name="Lululemon-color.svg" server="host.somad.ca/kahinpoura/" local="131997280760000000" remote="132002030400000000" Dst="2" />
<file name="Lululemon-white.svg" server="host.somad.ca/kahinpoura/" local="131997281480000000" remote="132002030400000000" Dst="2" />
<file name="mylogo-color.svg" server="host.somad.ca/kahinpoura/" local="131997253220000000" remote="132002030400000000" Dst="2" />
<file name="mylogo-white.svg" server="host.somad.ca/kahinpoura/" local="131997257120000000" remote="132002030400000000" Dst="2" />
<file name="NationalGeographic_color.svg" server="host.somad.ca/kahinpoura/" local="131997471020000000" remote="132002030400000000" Dst="2" />
<file name="NationalGeographic_white.svg" server="host.somad.ca/kahinpoura/" local="131997447180000000" remote="132002030400000000" Dst="2" />
<file name="WLA_color.svg" server="host.somad.ca/kahinpoura/" local="131997471580000000" remote="132002030400000000" Dst="2" />
<file name="WLA_white.svg" server="host.somad.ca/kahinpoura/" local="131997441320000000" remote="132002030400000000" Dst="2" />
<file name="logo-shipping-white.png" server="host.somad.ca/kahinpoura/" local="132000327880000000" remote="132002030400000000" Dst="2" />
<file name="_DS_Store" server="numbersmetcolours.com/public_html/" local="132020508600000000" remote="132020508600000000" Dst="2" />
<file name="choobchindecor-color.png" server="numbersmetcolours.com/public_html/" local="132020508600000000" remote="132020508600000000" Dst="2" />
<file name="choobchindecor_white.png" server="numbersmetcolours.com/public_html/" local="132020508600000000" remote="132020508600000000" Dst="2" />
<file name="CysticFibrosis-color.png" server="numbersmetcolours.com/public_html/" local="132020508600000000" remote="132020508600000000" Dst="2" />
<file name="CysticFibrosis-white.png" server="numbersmetcolours.com/public_html/" local="132020508600000000" remote="132020508600000000" Dst="2" />
<file name="Goal$-color.svg" server="numbersmetcolours.com/public_html/" local="132020508600000000" remote="132020508600000000" Dst="2" />
<file name="Goal$_white.svg" server="numbersmetcolours.com/public_html/" local="132020508600000000" remote="132020508600000000" Dst="2" />
<file name="logo-shipping-color.png" server="numbersmetcolours.com/public_html/" local="132020508600000000" remote="132020508600000000" Dst="2" />
<file name="logo-shipping-white.png" server="numbersmetcolours.com/public_html/" local="132020508600000000" remote="132020508600000000" Dst="2" />
<file name="Lululemon-color.svg" server="numbersmetcolours.com/public_html/" local="132020508600000000" remote="132020508600000000" Dst="2" />
<file name="Lululemon-white.svg" server="numbersmetcolours.com/public_html/" local="132020508600000000" remote="132020508600000000" Dst="2" />
<file name="mylogo-color.svg" server="numbersmetcolours.com/public_html/" local="132020508600000000" remote="132020508600000000" Dst="2" />
<file name="mylogo-white.svg" server="numbersmetcolours.com/public_html/" local="132020508600000000" remote="132020508600000000" Dst="2" />
<file name="NationalGeographic_color.svg" server="numbersmetcolours.com/public_html/" local="132020508600000000" remote="132020508600000000" Dst="2" />
<file name="NationalGeographic_white.svg" server="numbersmetcolours.com/public_html/" local="132020508600000000" remote="132020508600000000" Dst="2" />
<file name="WLA_color.svg" server="numbersmetcolours.com/public_html/" local="132020508600000000" remote="132020508600000000" Dst="2" />
<file name="WLA_white.svg" server="numbersmetcolours.com/public_html/" local="132020508600000000" remote="132020508600000000" Dst="2" />
</dwsync>